land/__main__.py
land/utils.py
jib-0.1.dist-info/METADATA
jib-0.1.dist-info/WHEEL
jib-0.1.dist-info/top_level.txt
jib-0.1.dist-info/RECORD
