Metadata-Version: 2.1
Name: jib
Version: 0.1
Summary: fly.
Home-page: http://github.com/neilyio/figur
Author: neilyio
Author-email: neil.hansen.31@gmail.com
License: MIT
Platform: UNKNOWN
